[
  { "name": "record_counts", "file": "profiling/profiler.ts", "notes": "Profiler public API" },
  { "name": "report", "file": "profiling/profiler.ts", "notes": "Profiler public API" },
  { "name": "initialize", "file": "project/project.ts", "notes": "Project public API" },
  { "name": "update_file", "file": "project/project.ts", "notes": "Project public API" },
  { "name": "remove_file", "file": "project/project.ts", "notes": "Project public API" },
  { "name": "get_stats", "file": "project/project.ts", "notes": "Project public API" },
  { "name": "get_call_graph", "file": "project/project.ts", "notes": "Project public API" },
  { "name": "get_all_scope_graphs", "file": "project/project.ts", "notes": "Project public API" },
  { "name": "get_dependents", "file": "project/project.ts", "notes": "Project public API" },
  { "name": "get_all_files", "file": "project/project.ts", "notes": "Project public API" },
  { "name": "get_index_single_file", "file": "project/project.ts", "notes": "Project public API" },
  { "name": "get_type_info", "file": "project/project.ts", "notes": "Project public API" },
  { "name": "get_derived_data", "file": "project/project.ts", "notes": "Project public API" },
  { "name": "get_source_code", "file": "project/project.ts", "notes": "Project public API" },
  { "name": "get_definition", "file": "project/project.ts", "notes": "Project public API" },
  { "name": "clear", "file": "project/project.ts", "notes": "Project public API" },
  { "name": "get_class_definitions", "file": "resolve_references/registries/definition.ts", "notes": "Used by entrypoint-analysis for constructor-to-class mapping" }
]
